pvx/__init__.py
pvx/env.py
pvx/pvx_cli.py
pvx/commands/__init__.py
pvx/commands/pvx_py_archive.py
pvx/commands/pvx_py_install.py
pvx/commands/pvx_py_list.py
pvx/commands/pvx_py_remove.py
pvx/commands/pvx_venv_activate.py
pvx/commands/pvx_venv_list.py
pvx/commands/pvx_venv_new.py
pvx/commands/pvx_venv_remove.py
pvx/commands/py_help.py
pvx/commands/venv_help.py
pvx/handler/__init__.py
pvx/handler/py.py
pvx/handler/venv.py
pvx/tools/__init__.py
pvx/tools/rich_pvx_console.py
pvx/tools/shell.py
pvx/tools/terminal.py
pvx/tools/utils.py
pvx-0.0.4.dist-info/LICENSE
pvx-0.0.4.dist-info/METADATA
pvx-0.0.4.dist-info/WHEEL
pvx-0.0.4.dist-info/entry_points.txt
pvx-0.0.4.dist-info/top_level.txt
pvx-0.0.4.dist-info/RECORD
