Metadata-Version: 2.1
Name: pvx
Version: 0.0.4
Summary: Python version & venv management
Home-page: https://github.com/JoJoJotarou/pvx
Author: JoJoJotarou
License: Apache-2.0 License
Project-URL: Bug Tracker, https://github.com/JoJoJotarou/pvx/issues
Platform: UNKNOWN
Classifier: Programming Language :: Python :: 3
Classifier: Operating System :: OS Independent
Requires-Python: >=3.6
License-File: LICENSE
Requires-Dist: click (==8.1.2)
Requires-Dist: pexpect (==4.8.0)
Requires-Dist: rich (==12.2.0)
